clarifyquestgen/__init__.py
clarifyquestgen/main_logic.py
clarifyquestgen-2025.5.151003.dist-info/licenses/LICENSE
clarifyquestgen-2025.5.151003.dist-info/METADATA
clarifyquestgen-2025.5.151003.dist-info/WHEEL
clarifyquestgen-2025.5.151003.dist-info/top_level.txt
clarifyquestgen-2025.5.151003.dist-info/RECORD
