Metadata-Version: 2.4
Name: clarifyquestgen
Version: 2025.5.151003
Summary: Clarifying Questions Generator for task refinement
Home-page: https://github.com/chigwell/ClarifyingQuestionsGenerator
Author: Eugene Evstafev
Author-email: chigwel@gmail.com
Classifier: Development Status :: 3 - Alpha
Classifier: Intended Audience :: Developers
Classifier: License :: OSI Approved :: MIT License
Classifier: Programming Language :: Python :: 3
Requires-Python: >=3.6
License-File: LICENSE
Requires-Dist: penelopa-dialog
Requires-Dist: gptintegration
Requires-Dist: TaskFeasibilityAnalyzer
Dynamic: author
Dynamic: author-email
Dynamic: classifier
Dynamic: description
Dynamic: description-content-type
Dynamic: home-page
Dynamic: license-file
Dynamic: requires-dist
Dynamic: requires-python
Dynamic: summary
